motormongo/__init__.py
motormongo/abstracts/__init__.py
motormongo/abstracts/document.py
motormongo/abstracts/embedded_document.py
motormongo/abstracts/exceptions/__init__.py
motormongo/abstracts/exceptions/document.py
motormongo/fields/__init__.py
motormongo/fields/binary_field.py
motormongo/fields/boolean_field.py
motormongo/fields/datetime_field.py
motormongo/fields/embedded_document_field.py
motormongo/fields/enum_field.py
motormongo/fields/exceptions/__init__.py
motormongo/fields/exceptions/binary_field.py
motormongo/fields/exceptions/boolean_field.py
motormongo/fields/exceptions/datetime_field.py
motormongo/fields/exceptions/embedded_document_field.py
motormongo/fields/exceptions/enum_field.py
motormongo/fields/exceptions/float_field.py
motormongo/fields/exceptions/geojson_field.py
motormongo/fields/exceptions/integer_field.py
motormongo/fields/exceptions/list_field.py
motormongo/fields/exceptions/reference_field.py
motormongo/fields/exceptions/string_field.py
motormongo/fields/field.py
motormongo/fields/float_field.py
motormongo/fields/geojson_field.py
motormongo/fields/integer_field.py
motormongo/fields/list_field.py
motormongo/fields/reference_field.py
motormongo/fields/string_field.py
motormongo/mongo/__init__.py
motormongo/mongo/database.py
motormongo/utils/__init__.py
motormongo/utils/formatter.py
motormongo/utils/logging.py
motormongo-0.1.19.dist-info/LICENSE
motormongo-0.1.19.dist-info/METADATA
motormongo-0.1.19.dist-info/WHEEL
motormongo-0.1.19.dist-info/entry_points.txt
motormongo-0.1.19.dist-info/RECORD
