Metadata-Version: 2.1
Name: motormongo
Version: 0.1.19
Summary: An asynchronous Object Document Mapper (ODM) for MongoDB built on top of Motor.
License: MIT
Author: pprunty
Author-email: pprunty@tcd.ie
Requires-Python: >=3.11,<4.0
Classifier: License :: OSI Approved :: MIT License
Classifier: Programming Language :: Python :: 3
Classifier: Programming Language :: Python :: 3.11
Classifier: Programming Language :: Python :: 3.12
Requires-Dist: motor (>=3.3.2,<4.0.0)
